.gitignore
.travis.yml
LICENSE
README.rst
setup.py
doc/example.cpp
doc/example_test.py
doc/index.rst
doc/references.bib
pybindcpp/__init__.py
pybindcpp/api.py
pybindcpp/helper.py
pybindcpp/module.py
pybindcpp/ufunc.py
pybindcpp/version.py
pybindcpp.egg-info/PKG-INFO
pybindcpp.egg-info/SOURCES.txt
pybindcpp.egg-info/dependency_links.txt
pybindcpp.egg-info/top_level.txt
pybindcpp/core/__init__.py
pybindcpp/core/ufunc.cpp
pybindcpp/ext/__init__.py
pybindcpp/ext/eigen.cpp
pybindcpp/ext/eigen_test.py
pybindcpp/ext/example.cpp
pybindcpp/ext/example_test.py
pybindcpp/ext/fftw.cpp
pybindcpp/ext/fftw_test.py
pybindcpp/ext/sample.cpp
pybindcpp/ext/sample_test.py
pybindcpp/ext/ufunc.cpp
pybindcpp/ext/ufunc_test.py
pybindcpp/include/pybindcpp/api.h
pybindcpp/include/pybindcpp/ctypes.h
pybindcpp/include/pybindcpp/module.h
pybindcpp/include/pybindcpp/ufunc.h