Metadata-Version: 1.0
Name: pybindcpp
Version: 0.1
Summary: Python Bindings from C++
Home-page: UNKNOWN
Author: Dzhelil Rufat
Author-email: d@rufat.be
License: GPLv3
Platform: UNKNOWN
